{
  "id": "home_map",
  "type": "SharedSlice",
  "name": "HomeMap",
  "description": "HomeMap",
  "variations": [
    {
      "id": "default",
      "name": "Default",
      "docURL": "...",
      "version": "initial",
      "description": "Default",
      "imageUrl": "",
      "primary": {
        "title": {
          "type": "StructuredText",
          "config": {
            "label": "Title",
            "placeholder": "",
            "allowTargetBlank": true,
            "multi": "heading2,strong,em"
          }
        },
        "description": {
          "type": "StructuredText",
          "config": {
            "label": "Description",
            "placeholder": "",
            "allowTargetBlank": true,
            "multi": "paragraph,strong,em"
          }
        }
      },
      "items": {}
    }
  ]
}